maxwell/DEMON.txt
maxwell/__init__.py
maxwell/__main__.py
maxwell/api.py
maxwell/cli.py
maxwell/config.py
maxwell/discovery.py
maxwell/extractors.py
maxwell/filesystem.py
maxwell/lm_pool.py
maxwell/mcp_server.py
maxwell/pydantic_gbnf.py
maxwell/registry.py
maxwell/reporting.py
maxwell/rules.py
maxwell/storage.py
maxwell/types.py
maxwell/utils.py
maxwell/workflows/__init__.py
maxwell/workflows/ast_analysis.py
maxwell/workflows/base.py
maxwell/workflows/deep_research.py
maxwell/workflows/snapshot.py
maxwell/workflows/tag_refactor.py
maxwell/workflows/utilities.py
maxwell/workflows/chat/README.md
maxwell/workflows/chat/__init__.py
maxwell/workflows/chat/backup_strategy.py
maxwell/workflows/chat/batch_extract.py
maxwell/workflows/chat/bm25_search.py
maxwell/workflows/chat/data_quality.py
maxwell/workflows/chat/incremental_processor.py
maxwell/workflows/chat/metadata_extractor.py
maxwell/workflows/chat/parsers.py
maxwell/workflows/chat/semantic_search.py
maxwell/workflows/justification/README.md
maxwell/workflows/justification/__init__.py
maxwell/workflows/justification/complete_justification.py
maxwell/workflows/justification/context_builder.py
maxwell/workflows/justification/file_analyzer.py
maxwell/workflows/justification/llm_analyzer.py
maxwell/workflows/justification/quality_checks.py
maxwell/workflows/justification/worksheet_manager.py
maxwell/workflows/validate/__init__.py
maxwell/workflows/validate/ast_utils.py
maxwell/workflows/validate/validation_engine.py
maxwell/workflows/validate/validators/__init__.py
maxwell/workflows/validate/validators/types.py
maxwell/workflows/validate/validators/project_wide/__init__.py
maxwell/workflows/validate/validators/single_file/__init__.py
maxwell/workflows/validate/validators/single_file/dict_get_fallback.py
maxwell/workflows/validate/validators/single_file/emoji.py
maxwell/workflows/validate/validators/single_file/exports.py
maxwell/workflows/validate/validators/single_file/logger_names.py
maxwell_demon-0.1.0.dist-info/licenses/LICENSE
maxwell_demon-0.1.0.dist-info/METADATA
maxwell_demon-0.1.0.dist-info/WHEEL
maxwell_demon-0.1.0.dist-info/entry_points.txt
maxwell_demon-0.1.0.dist-info/top_level.txt
maxwell_demon-0.1.0.dist-info/RECORD
