Metadata-Version: 2.4
Name: maxwell-demon
Version: 0.1.0
Summary: Semantic workflow automation for codebases and documents - CLI-first tool for content analysis, search, and code quality.
Author-email: Mithran Mohanraj <mithran.mohanraj@gmail.com>
License: MIT
Project-URL: Homepage, https://github.com/mithranm/maxwell-file-demon
Project-URL: Bug Tracker, https://github.com/mithranm/maxwell-file-demon/issues
Classifier: Development Status :: 3 - Alpha
Classifier: Environment :: Console
Classifier: Intended Audience :: Developers
Classifier: License :: OSI Approved :: MIT License
Classifier: Programming Language :: Python :: 3
Classifier: Programming Language :: Python :: 3.11
Classifier: Programming Language :: Python :: 3.12
Classifier: Programming Language :: Python :: 3.13
Classifier: Topic :: Software Development :: Quality Assurance
Requires-Python: >=3.11
License-File: LICENSE
Requires-Dist: pydantic>=2.0
Requires-Dist: rich>=12.0
Requires-Dist: tomli-w
Requires-Dist: python-dotenv>=1.0
Requires-Dist: libcst
Requires-Dist: requests>=2.25
Provides-Extra: chat
Requires-Dist: pymongo>=4.0; extra == "chat"
Requires-Dist: qdrant-client>=1.0; extra == "chat"
Requires-Dist: rank-bm25>=0.2; extra == "chat"
Requires-Dist: numpy>=1.21; extra == "chat"
Provides-Extra: docs
Requires-Dist: marker-pdf>=0.2; extra == "docs"
Requires-Dist: markitdown>=0.0.1; extra == "docs"
Provides-Extra: mcp
Requires-Dist: mcp>=0.1; extra == "mcp"
Provides-Extra: all
Requires-Dist: pymongo>=4.0; extra == "all"
Requires-Dist: qdrant-client>=1.0; extra == "all"
Requires-Dist: rank-bm25>=0.2; extra == "all"
Requires-Dist: numpy>=1.21; extra == "all"
Requires-Dist: marker-pdf>=0.2; extra == "all"
Requires-Dist: markitdown>=0.0.1; extra == "all"
Requires-Dist: mcp>=0.1; extra == "all"
Provides-Extra: dev
Requires-Dist: pytest>=7.0; extra == "dev"
Requires-Dist: pytest-cov>=4.0; extra == "dev"
Requires-Dist: pytest-asyncio>=0.21; extra == "dev"
Requires-Dist: ruff>=0.1; extra == "dev"
Requires-Dist: black>=23.0; extra == "dev"
Dynamic: license-file
